mean_differences_mc/__init__.py
mean_differences_mc/calculate_mean_difference.py
mean_differences_mc/generalized_monte_carlo_test.py
mean_differences_mc/index_switch.py
mean_differences_mc/switch_elements.py
mean_differences_mc/tester_significant_difference.py
mean_differences_mc-0.1.0.dist-info/LICENSE
mean_differences_mc-0.1.0.dist-info/WHEEL
mean_differences_mc-0.1.0.dist-info/METADATA
mean_differences_mc-0.1.0.dist-info/RECORD
